test_package/__init__.py
test_package/__main__.py
test_package/modules.py
test_keti_test-0.1.dist-info/LICENSE
test_keti_test-0.1.dist-info/METADATA
test_keti_test-0.1.dist-info/WHEEL
test_keti_test-0.1.dist-info/entry_points.txt
test_keti_test-0.1.dist-info/top_level.txt
test_keti_test-0.1.dist-info/RECORD
