Metadata-Version: 2.1
Name: test-keti-test
Version: 0.1
Summary: test package
Home-page: https://github.com/Mishuni/Pip_Package_Practice.git
Author: test1234
Author-email: test1234@email.re.kr
License: UNKNOWN
Platform: UNKNOWN
Requires-Python: >=3.6
License-File: LICENSE
Requires-Dist: Flask
